nats_tools/__about__.py
nats_tools/__init__.py
nats_tools/monitor.py
nats_tools/natsd.py
nats_tools/testing.py
nats_tools/templates/__init__.py
nats_tools/templates/config.py
nats_tools/templates/utils.py
nats_tools-1.0.2.dist-info/METADATA
nats_tools-1.0.2.dist-info/WHEEL
nats_tools-1.0.2.dist-info/entry_points.txt
nats_tools-1.0.2.dist-info/top_level.txt
nats_tools-1.0.2.dist-info/RECORD
