Metadata-Version: 2.1
Name: nats-tools
Version: 1.0.2
Summary: Useful tools to develop Python projects relying on NATS
Author-email: Guillaume Charbonnier <guillaume.charbonnier@araymond.com>
License: Apache-2.0
Project-URL: Repository, https://github.com/quara-dev/nats-tools
Project-URL: Issues, https://github.com/quara-dev/nats-tools/issues
Classifier: Programming Language :: Python :: 3
Classifier: License :: OSI Approved :: Apache Software License
Requires-Python: <4.0,>=3.8
Requires-Dist: httpx
Requires-Dist: jinja2
Provides-Extra: build
Requires-Dist: build ; extra == 'build'
Requires-Dist: invoke ; extra == 'build'
Requires-Dist: pip-tools ; extra == 'build'
Provides-Extra: dev
Requires-Dist: black ; extra == 'dev'
Requires-Dist: isort ; extra == 'dev'
Requires-Dist: invoke ; extra == 'dev'
Requires-Dist: flake8 ; extra == 'dev'
Requires-Dist: mypy ; extra == 'dev'
Requires-Dist: pytest ; extra == 'dev'
Requires-Dist: pytest-asyncio ; extra == 'dev'
Requires-Dist: pytest-cov ; extra == 'dev'
Requires-Dist: types-setuptools ; extra == 'dev'
Provides-Extra: docs
Requires-Dist: mkdocs-gen-files ; extra == 'docs'
Requires-Dist: mkdocs-literate-nav ; extra == 'docs'
Requires-Dist: mkdocs-material ; extra == 'docs'
Requires-Dist: mkdocs-section-index ; extra == 'docs'
Requires-Dist: mkdocstrings[python] ; extra == 'docs'
Requires-Dist: pymdown-extensions ; extra == 'docs'
